sqliteframe/__init__.py
sqliteframe/database.py
sqliteframe/entity/__init__.py
sqliteframe/entity/column.py
sqliteframe/entity/entity.py
sqliteframe/entity/preserve_order.py
sqliteframe/foreign_key/__init__.py
sqliteframe/foreign_key/foreign_key.py
sqliteframe/foreign_key/restraints.py
sqliteframe/join/__init__.py
sqliteframe/join/join.py
sqliteframe/join/join_types.py
sqliteframe/order_by/__init__.py
sqliteframe/order_by/order_by.py
sqliteframe/order_by/order_types.py
sqliteframe/parameterized/__init__.py
sqliteframe/parameterized/parameterized.py
sqliteframe/pragma/__init__.py
sqliteframe/pragma/statements.py
sqliteframe/pragma/types.py
sqliteframe/result/__init__.py
sqliteframe/result/result.py
sqliteframe/statements/__init__.py
sqliteframe/statements/create_table.py
sqliteframe/statements/delete_from.py
sqliteframe/statements/drop_table.py
sqliteframe/statements/insert_into.py
sqliteframe/statements/pragma.py
sqliteframe/statements/select.py
sqliteframe/statements/set.py
sqliteframe/statements/statement.py
sqliteframe/suggested_schema/__init__.py
sqliteframe/suggested_schema/column.py
sqliteframe/suggested_schema/fk_column.py
sqliteframe/suggested_schema/schema.py
sqliteframe/suggested_schema/table.py
sqliteframe/suggested_schema/unknown_type.py
sqliteframe/types/__init__.py
sqliteframe/types/blob.py
sqliteframe/types/boolean.py
sqliteframe/types/date.py
sqliteframe/types/float.py
sqliteframe/types/integer.py
sqliteframe/types/null.py
sqliteframe/types/string.py
sqliteframe/types/time.py
sqliteframe/types/type.py
sqliteframe/types/types.py
sqliteframe/where/__init__.py
sqliteframe/where/comparisons.py
sqliteframe/where/condition.py
sqliteframe/where/conjunctions.py
sqliteframe/where/where.py
sqliteframe/wildcards/__init__.py
sqliteframe/wildcards/wildcards.py
SQLiteFrame-0.3.1.dist-info/LICENSE
SQLiteFrame-0.3.1.dist-info/METADATA
SQLiteFrame-0.3.1.dist-info/WHEEL
SQLiteFrame-0.3.1.dist-info/top_level.txt
SQLiteFrame-0.3.1.dist-info/RECORD
