Metadata-Version: 2.1
Name: SQLiteFrame
Version: 0.3.1
Summary: A lightweight, zero-dependency ORM for SQLite in Python
Author-email: Kieran Lock <kieran.lock@outlook.com>
License: MIT License
Project-URL: GitHub, https://github.com/Kieran-Lock/SQLiteFrame
Project-URL: Documentation, https://sqliteframe-documentation.vercel.app/
Project-URL: License, https://github.com/Kieran-Lock/SQLiteFrame/blob/master/LICENSE
Keywords: orm,sqlite3,schematics,lightweight,zero-dependency
Classifier: Development Status :: 3 - Alpha
Classifier: License :: OSI Approved :: MIT License
Classifier: Programming Language :: Python :: 3.8
Classifier: Intended Audience :: Developers
Requires-Python: >=3.8
License-File: LICENSE
